LICENSE
README.md
setup.cfg
setup.py
pylgbst/__init__.py
pylgbst/hub.py
pylgbst/messages.py
pylgbst/peripherals.py
pylgbst/utilities.py
pylgbst.egg-info/PKG-INFO
pylgbst.egg-info/SOURCES.txt
pylgbst.egg-info/dependency_links.txt
pylgbst.egg-info/requires.txt
pylgbst.egg-info/top_level.txt
pylgbst/comms/__init__.py
pylgbst/comms/cbleak.py
pylgbst/comms/cbluepy.py
pylgbst/comms/cgatt.py
pylgbst/comms/cgattlib.py
pylgbst/comms/cpygatt.py
tests/test_cbleak.py
tests/test_cbluepy.py
tests/test_comms.py
tests/test_gatt.py
tests/test_hub.py
tests/test_peripherals.py
tests/test_pygatt.py